{"id": "861", "title": "dsdsf", "author": "fdsfsd", "year": "2025-03-07T08:11:19.398749", "version": "dfsdf"}
{"id": "213", "title": "fdsfdfd", "author": "dsfdsf", "year": "2025-03-07T08:16:28.084048", "version": "dfdsfds"}
{"id": "834", "title": "dfdsfds", "author": "dsfsdfs", "year": "2025-03-07T08:16:36.045254", "version": "fsdfsd"}
{"id": "735", "title": "dsfdsfdsf", "author": "sdfsdf", "year": "2025-03-07T08:16:40.952659", "version": "fdsf"}
{"id": "983", "title": "dsfdsfdsf", "author": "dfsdf", "year": "2025-03-07T08:16:45.926006", "version": "sdfdsf"}
{"id": "412", "title": "sdfsdf", "author": "sdfdsf", "year": "2025-03-07T08:16:51.683292", "version": "dfdsfsdf"}
{"id": "521", "title": "dfsfsf", "author": "dfsdfsdf", "year": "2025-03-07T08:17:08.375070", "version": "fsdfsdsd"}
{"id": "764", "title": "dfsdfsf", "author": "dsfsfs", "year": "2025-03-07T08:17:19.041686", "version": "fsdfsdfsdf"}
{"id": "754", "title": "dfdsfsdf", "author": "sdfsdf", "year": "2025-03-07T08:17:28.426989", "version": "sdfdsf"}
{"id": "125", "title": "dfsdfsdfsd", "author": "dfsdfsdfs", "year": "2025-03-07T08:17:33.653656", "version": "sdfdsfsdfsdf"}
{"id": "589", "title": "dfsdfsdfsd", "author": "dsfsdfsdf", "year": "2025-03-07T08:17:38.873064", "version": "dfsdfsd"}
{"id": "395", "title": "dfsdfdsfsdf", "author": "dfsdfsdf", "year": "2025-03-07T08:19:02.298422", "version": "sdfsdfsdsf"}
